st_audiorec/__init__.py
streamlit_audiorec_ru_fork-0.1.6.dist-info/LICENCE
streamlit_audiorec_ru_fork-0.1.6.dist-info/METADATA
streamlit_audiorec_ru_fork-0.1.6.dist-info/WHEEL
streamlit_audiorec_ru_fork-0.1.6.dist-info/top_level.txt
streamlit_audiorec_ru_fork-0.1.6.dist-info/RECORD
