Metadata-Version: 2.1
Name: streamlit-audiorec-ru-fork
Version: 0.1.6
Summary: Record audio from the user's microphone in apps that are deployed to the web. (via Browser Media-API) [GitHub ☆ 160+: steamlit-audio-recorder]
Home-page: https://github.com/BondarchukGleb42/streamlit-audio-recorder
Author: Stefan Rummer
Author-email: djgleban1147@gmail.com
Requires-Python: >=3.7
License-File: LICENCE
Requires-Dist: streamlit>=0.63
